obs/__init__.py
obs/auth.py
obs/bucket.py
obs/bulktasks.py
obs/cache.py
obs/client.py
obs/const.py
obs/convertor.py
obs/crypto_client.py
obs/extension.py
obs/http2.py
obs/ilog.py
obs/loadtoken.py
obs/locks.py
obs/model.py
obs/obs_cipher_suite.py
obs/progress.py
obs/searchmethod.py
obs/transfer.py
obs/util.py
obs/workflow.py
huawei_obs_sdk-3.22.2.dist-info/METADATA
huawei_obs_sdk-3.22.2.dist-info/WHEEL
huawei_obs_sdk-3.22.2.dist-info/top_level.txt
huawei_obs_sdk-3.22.2.dist-info/RECORD
