Metadata-Version: 2.1
Name: huawei-obs-sdk
Version: 3.22.2
Summary: OBS Python SDK
Home-page: 
License: Apache-2.0
Keywords: obs,python
Platform: Independant
Requires-Dist: pycryptodome (>=3.10.1)
